Metadata-Version: 2.1
Name: notefluid
Version: 0.0.21
Summary: notefluid
Home-page: https://github.com/1007530194
Author: niult
Author-email: 1007530194@qq.com
License: UNKNOWN
Platform: UNKNOWN
License-File: LICENSE
Requires-Dist: notefluid
Requires-Dist: numpy
Requires-Dist: scipy
